streamlit_chat_plus/__init__.py
streamlit_chat_plus/frontend/build/asset-manifest.json
streamlit_chat_plus/frontend/build/bootstrap.min.css
streamlit_chat_plus/frontend/build/bootstrap.min.css.map
streamlit_chat_plus/frontend/build/index.html
streamlit_chat_plus/frontend/build/precache-manifest.1de38f33c8928e4f9877c6c671d88c26.js
streamlit_chat_plus/frontend/build/service-worker.js
streamlit_chat_plus/frontend/build/static/css/2.fbbf07ed.chunk.css
streamlit_chat_plus/frontend/build/static/css/2.fbbf07ed.chunk.css.map
streamlit_chat_plus/frontend/build/static/css/main.87864c03.chunk.css
streamlit_chat_plus/frontend/build/static/css/main.87864c03.chunk.css.map
streamlit_chat_plus/frontend/build/static/js/2.5a1388d3.chunk.js
streamlit_chat_plus/frontend/build/static/js/2.5a1388d3.chunk.js.LICENSE.txt
streamlit_chat_plus/frontend/build/static/js/2.5a1388d3.chunk.js.map
streamlit_chat_plus/frontend/build/static/js/main.59f02cc6.chunk.js
streamlit_chat_plus/frontend/build/static/js/main.59f02cc6.chunk.js.map
streamlit_chat_plus/frontend/build/static/js/runtime-main.44d30fc2.js
streamlit_chat_plus/frontend/build/static/js/runtime-main.44d30fc2.js.map
streamlit_chat_plus-0.0.0.3.dist-info/LICENSE
streamlit_chat_plus-0.0.0.3.dist-info/METADATA
streamlit_chat_plus-0.0.0.3.dist-info/WHEEL
streamlit_chat_plus-0.0.0.3.dist-info/top_level.txt
streamlit_chat_plus-0.0.0.3.dist-info/RECORD
