Metadata-Version: 2.1
Name: streamlit-chat-plus
Version: 0.0.0.3
Summary: A streamlit component, to make chatbots
Home-page: https://github.com/osala-eng/st-chat-plus
Author: Jashon Osala, Yash Pravin Pawar, Yash Vardhan Kapil
Author-email: jashonosala@gmail.com
Keywords: chat streamlit streamlit-component
Classifier: Programming Language :: Python :: 3
Classifier: Operating System :: OS Independent
Requires-Python: >=3.8
License-File: LICENSE
Requires-Dist: streamlit (>=0.63)
